{
  "version": "1.0",
  "created_at": "2025-08-16T09:01:48.099433",
  "session_id": 4383125056,
  "session_start_time": "2025-08-16T09:01:48.097167",
  "repo_url": "https://github.com/NoMore201/googleplay-api",
  "total_steps": 5,
  "completed_steps": [
    {
      "step_name": "Repository Discovery",
      "success": false,
      "summary": "Failed to discover repository: GitHubClient.get_repository() missing 1 required positional argument: 'repo'",
      "completed_at": "2025-08-16T09:01:48.099438",
      "data": null,
      "metrics": null
    }
  ],
  "context": {
    "repo_url": "https://github.com/NoMore201/googleplay-api"
  },
  "confirmation_count": 0,
  "session_metrics": {
    "session_start_time": "2025-08-16 09:01:48.097167",
    "session_duration": "0:00:00.002276",
    "total_steps": 5,
    "completed_steps": 1,
    "successful_steps": 0,
    "failed_steps": 1,
    "completion_rate": 0.2,
    "success_rate": 0.0,
    "total_confirmations": 0,
    "avg_time_per_step": "0:00:00.002276"
  }
}